citegeist/__init__.py
citegeist/py.typed
citegeist/core/__init__.py
citegeist/core/analysis_functions.py
citegeist/core/checkpoints.py
citegeist/core/citegeist_model.py
citegeist/core/gurobi_impl.py
citegeist/core/utils.py
citegeist-0.1.1.dist-info/LICENSE
citegeist-0.1.1.dist-info/METADATA
citegeist-0.1.1.dist-info/WHEEL
citegeist-0.1.1.dist-info/top_level.txt
citegeist-0.1.1.dist-info/RECORD
