Metadata-Version: 2.2
Name: citegeist
Version: 0.1.1
Summary: A spatial transcriptomics deconvolution tool for cell type identification and gene expression analysis
Home-page: https://github.com/acc383/CITEgeist
Author: Alexander Chang, Brent T. Schlegel
Author-email: alc376@pitt.edu
Classifier: Development Status :: 4 - Beta
Classifier: Intended Audience :: Science/Research
Classifier: License :: OSI Approved :: BSD License
Classifier: Programming Language :: Python :: 3
Classifier: Programming Language :: Python :: 3.8
Classifier: Programming Language :: Python :: 3.9
Classifier: Programming Language :: Python :: 3.10
Classifier: Topic :: Scientific/Engineering :: Bio-Informatics
Requires-Python: >=3.8
License-File: LICENSE
Requires-Dist: numpy>=1.20.0
Requires-Dist: pandas>=1.3.0
Requires-Dist: scanpy>=1.9.0
Requires-Dist: scipy>=1.7.0
Requires-Dist: pyarrow>=5.0.0
Requires-Dist: gurobipy>=9.5.0
Requires-Dist: squidpy>=1.6.2
Provides-Extra: dev
Requires-Dist: pytest>=7.0.0; extra == "dev"
Requires-Dist: pytest-cov>=3.0.0; extra == "dev"
Requires-Dist: black>=22.0.0; extra == "dev"
Requires-Dist: isort>=5.10.0; extra == "dev"
Dynamic: author
Dynamic: author-email
Dynamic: classifier
Dynamic: description
Dynamic: description-content-type
Dynamic: home-page
Dynamic: provides-extra
Dynamic: requires-dist
Dynamic: requires-python
Dynamic: summary
